<?xml version="1.0" encoding="UTF-8"?>
<SFunction>
	<Types>
		<EnumType name="boolean">
			<EnumValue name="false" ordinal="0" />
			<EnumValue name="true" ordinal="1" />
		</EnumType>
	</Types>
	<Inports debug="true">
		<Inport portNr="1" type="boolean" signalName="obstacle_detection">
			<ScalarRefs>
				<ScalarRef displayName="obstacle_detection">OUTPUT:obstacle_detection</ScalarRef>
			</ScalarRefs>
		</Inport>
		<Inport portNr="2" type="boolean" signalName="moveUp">
			<ScalarRefs>
				<ScalarRef displayName="move_up">OUTPUT:move_up</ScalarRef>
			</ScalarRefs>
		</Inport>
		<Inport portNr="3" type="boolean" signalName="moveDown">
			<ScalarRefs>
				<ScalarRef displayName="move_down">OUTPUT:move_down</ScalarRef>
			</ScalarRefs>
		</Inport>
	</Inports>
</SFunction>
