<?xml version="1.0" encoding="UTF-8"?>
<SFunction>
	<Types>
		<EnumType name="boolean">
			<EnumValue name="false" ordinal="0" />
			<EnumValue name="true" ordinal="1" />
		</EnumType>
	</Types>
	<Inports>
		<Inport portNr="1" type="boolean">
			<ScalarRefs>
				<ScalarRef>OUTPUT:obstacle_detection</ScalarRef>
			</ScalarRefs>
		</Inport>
		<Inport portNr="2" type="boolean">
			<ScalarRefs>
				<ScalarRef>OUTPUT:move_up</ScalarRef>
			</ScalarRefs>
		</Inport>
		<Inport portNr="3" type="boolean">
			<ScalarRefs>
				<ScalarRef>OUTPUT:move_down</ScalarRef>
			</ScalarRefs>
		</Inport>
	</Inports>
</SFunction>
